Metadata-Version: 2.1
Name: apolloapi
Version: 0.0.6
Summary: 操作apollo的python客户端
Home-page: UNKNOWN
Author: feichenxue
Author-email: 986024058@qq.com
License: UNKNOWN
Platform: UNKNOWN
